{
  "basis": "CFS",
  "accounts": [
    {
      "rcept_no": "20241114002984",
      "reprt_code": "11014",
      "bsns_year": "2024",
      "corp_code": "00688996",
      "stock_code": "105560",
      "fs_div": "CFS",
      "fs_nm": "연결재무제표",
      "sj_div": "BS",
      "sj_nm": "재무상태표",
      "account_nm": "자산총계",
      "thstrm_nm": "제 17 기3분기말",
      "thstrm_dt": "2024.09.30 현재",
      "thstrm_amount": "745,334,299,000,000",
      "frmtrm_nm": "제 16 기말",
      "frmtrm_dt": "2023.12.31 현재",
      "frmtrm_amount": "715,738,152,000,000",
      "ord": "5",
      "currency": "KRW"
    },
    {
      "rcept_no": "20241114002984",
      "reprt_code": "11014",
      "bsns_year": "2024",
      "corp_code": "00688996",
      "stock_code": "105560",
      "fs_div": "CFS",
      "fs_nm": "연결재무제표",
      "sj_div": "BS",
      "sj_nm": "재무상태표",
      "account_nm": "부채총계",
      "thstrm_nm": "제 17 기3분기말",
      "thstrm_dt": "2024.09.30 현재",
      "thstrm_amount": "685,424,283,000,000",
      "frmtrm_nm": "제 16 기말",
      "frmtrm_dt": "2023.12.31 현재",
      "frmtrm_amount": "656,864,842,000,000",
      "ord": "11",
      "currency": "KRW"
    },
    {
      "rcept_no": "20241114002984",
      "reprt_code": "11014",
      "bsns_year": "2024",
      "corp_code": "00688996",
      "stock_code": "105560",
      "fs_div": "CFS",
      "fs_nm": "연결재무제표",
      "sj_div": "BS",
      "sj_nm": "재무상태표",
      "account_nm": "자본금",
      "thstrm_nm": "제 17 기3분기말",
      "thstrm_dt": "2024.09.30 현재",
      "thstrm_amount": "2,090,558,000,000",
      "frmtrm_nm": "제 16 기말",
      "frmtrm_dt": "2023.12.31 현재",
      "frmtrm_amount": "2,090,558,000,000",
      "ord": "13",
      "currency": "KRW"
    },
    {
      "rcept_no": "20241114002984",
      "reprt_code": "11014",
      "bsns_year": "2024",
      "corp_code": "00688996",
      "stock_code": "105560",
      "fs_div": "CFS",
      "fs_nm": "연결재무제표",
      "sj_div": "BS",
      "sj_nm": "재무상태표",
      "account_nm": "이익잉여금",
      "thstrm_nm": "제 17 기3분기말",
      "thstrm_dt": "2024.09.30 현재",
      "thstrm_amount": "34,569,260,000,000",
      "frmtrm_nm": "제 16 기말",
      "frmtrm_dt": "2023.12.31 현재",
      "frmtrm_amount": "32,029,199,000,000",
      "ord": "17",
      "currency": "KRW"
    },
    {
      "rcept_no": "20241114002984",
      "reprt_code": "11014",
      "bsns_year": "2024",
      "corp_code": "00688996",
      "stock_code": "105560",
      "fs_div": "CFS",
      "fs_nm": "연결재무제표",
      "sj_div": "BS",
      "sj_nm": "재무상태표",
      "account_nm": "자본총계",
      "thstrm_nm": "제 17 기3분기말",
      "thstrm_dt": "2024.09.30 현재",
      "thstrm_amount": "59,910,016,000,000",
      "frmtrm_nm": "제 16 기말",
      "frmtrm_dt": "2023.12.31 현재",
      "frmtrm_amount": "58,873,310,000,000",
      "ord": "21",
      "currency": "KRW"
    },
    {
      "rcept_no": "20241114002984",
      "reprt_code": "11014",
      "bsns_year": "2024",
      "corp_code": "00688996",
      "stock_code": "105560",
      "fs_div": "CFS",
      "fs_nm": "연결재무제표",
      "sj_div": "IS",
      "sj_nm": "손익계산서",
      "account_nm": "법인세차감전 순이익",
      "thstrm_nm": "제 17 기3분기",
      "thstrm_dt": "2024.01.01 ~ 2024.09.30",
      "thstrm_amount": "2,284,151,000,000",
      "thstrm_add_amount": "6,060,867,000,000",
      "frmtrm_nm": "제 16 기3분기",
      "frmtrm_dt": "2023.01.01 ~ 2023.09.30",
      "frmtrm_add_amount": "5,907,413,000,000",
      "frmtrm_amount": "1,903,078,000,000",
      "ord": "27",
      "currency": "KRW"
    },
    {
      "rcept_no": "20241114002984",
      "reprt_code": "11014",
      "bsns_year": "2024",
      "corp_code": "00688996",
      "stock_code": "105560",
      "fs_div": "CFS",
      "fs_nm": "연결재무제표",
      "sj_div": "IS",
      "sj_nm": "손익계산서",
      "account_nm": "당기순이익(손실)",
      "thstrm_nm": "제 17 기3분기",
      "thstrm_dt": "2024.01.01 ~ 2024.09.30",
      "thstrm_amount": "1,596,039,000,000",
      "thstrm_add_amount": "4,369,918,000,000",
      "frmtrm_nm": "제 16 기3분기",
      "frmtrm_dt": "2023.01.01 ~ 2023.09.30",
      "frmtrm_add_amount": "4,352,027,000,000",
      "frmtrm_amount": "1,337,105,000,000",
      "ord": "29",
      "currency": "KRW"
    },
    {
      "rcept_no": "20241114002984",
      "reprt_code": "11014",
      "bsns_year": "2024",
      "corp_code": "00688996",
      "stock_code": "105560",
      "fs_div": "CFS",
      "fs_nm": "연결재무제표",
      "sj_div": "BS",
      "sj_nm": "재무상태표",
      "account_nm": "예수부채",
      "thstrm_nm": "제 17 기3분기말",
      "thstrm_dt": "2024.09.30 현재",
      "thstrm_amount": "423,538,438,000,000",
      "frmtrm_nm": "제 16 기말",
      "frmtrm_dt": "2023.12.31 현재",
      "frmtrm_amount": "406,512,434,000,000",
      "ord": "31",
      "currency": "KRW"
    },
    {
      "rcept_no": "20241114002984",
      "reprt_code": "11014",
      "bsns_year": "2024",
      "corp_code": "00688996",
      "stock_code": "105560",
      "fs_div": "CFS",
      "fs_nm": "연결재무제표",
      "sj_div": "BS",
      "sj_nm": "재무상태표",
      "account_nm": "당기손익-공정가치측정금융자산",
      "thstrm_nm": "제 17 기3분기말",
      "thstrm_dt": "2024.09.30 현재",
      "thstrm_amount": "76,935,965,000,000",
      "frmtrm_nm": "제 16 기말",
      "frmtrm_dt": "2023.12.31 현재",
      "frmtrm_amount": "77,038,267,000,000",
      "ord": "35",
      "currency": "KRW"
    },
    {
      "rcept_no": "20241114002984",
      "reprt_code": "11014",
      "bsns_year": "2024",
      "corp_code": "00688996",
      "stock_code": "105560",
      "fs_div": "CFS",
      "fs_nm": "연결재무제표",
      "sj_div": "BS",
      "sj_nm": "재무상태표",
      "account_nm": "보험계약자산",
      "thstrm_nm": "제 17 기3분기말",
      "thstrm_dt": "2024.09.30 현재",
      "thstrm_amount": "312,757,000,000",
      "frmtrm_nm": "제 16 기말",
      "frmtrm_dt": "2023.12.31 현재",
      "frmtrm_amount": "229,640,000,000",
      "ord": "41",
      "currency": "KRW"
    },
    {
      "rcept_no": "20241114002984",
      "reprt_code": "11014",
      "bsns_year": "2024",
      "corp_code": "00688996",
      "stock_code": "105560",
      "fs_div": "CFS",
      "fs_nm": "연결재무제표",
      "sj_div": "BS",
      "sj_nm": "재무상태표",
      "account_nm": "보험계약부채",
      "thstrm_nm": "제 17 기3분기말",
      "thstrm_dt": "2024.09.30 현재",
      "thstrm_amount": "55,153,985,000,000",
      "frmtrm_nm": "제 16 기말",
      "frmtrm_dt": "2023.12.31 현재",
      "frmtrm_amount": "50,308,552,000,000",
      "ord": "43",
      "currency": "KRW"
    },
    {
      "rcept_no": "20241114002984",
      "reprt_code": "11014",
      "bsns_year": "2024",
      "corp_code": "00688996",
      "stock_code": "105560",
      "fs_div": "CFS",
      "fs_nm": "연결재무제표",
      "sj_div": "BS",
      "sj_nm": "재무상태표",
      "account_nm": "파생상품자산",
      "thstrm_nm": "제 17 기3분기말",
      "thstrm_dt": "2024.09.30 현재",
      "thstrm_amount": "5,729,437,000,000",
      "frmtrm_nm": "제 16 기말",
      "frmtrm_dt": "2023.12.31 현재",
      "frmtrm_amount": "6,157,628,000,000",
      "ord": "47",
      "currency": "KRW"
    },
    {
      "rcept_no": "20241114002984",
      "reprt_code": "11014",
      "bsns_year": "2024",
      "corp_code": "00688996",
      "stock_code": "105560",
      "fs_div": "CFS",
      "fs_nm": "연결재무제표",
      "sj_div": "BS",
      "sj_nm": "재무상태표",
      "account_nm": "파생상품부채",
      "thstrm_nm": "제 17 기3분기말",
      "thstrm_dt": "2024.09.30 현재",
      "thstrm_amount": "5,336,320,000,000",
      "frmtrm_nm": "제 16 기말",
      "frmtrm_dt": "2023.12.31 현재",
      "frmtrm_amount": "6,210,639,000,000",
      "ord": "49",
      "currency": "KRW"
    },
    {
      "rcept_no": "20241114002984",
      "reprt_code": "11014",
      "bsns_year": "2024",
      "corp_code": "00688996",
      "stock_code": "105560",
      "fs_div": "CFS",
      "fs_nm": "연결재무제표",
      "sj_div": "IS",
      "sj_nm": "손익계산서",
      "account_nm": "순이자손익",
      "thstrm_nm": "제 17 기3분기",
      "thstrm_dt": "2024.01.01 ~ 2024.09.30",
      "thstrm_amount": "3,164,967,000,000",
      "thstrm_add_amount": "9,522,689,000,000",
      "frmtrm_nm": "제 16 기3분기",
      "frmtrm_dt": "2023.01.01 ~ 2023.09.30",
      "frmtrm_add_amount": "8,958,317,000,000",
      "frmtrm_amount": "3,124,648,000,000",
      "ord": "51",
      "currency": "KRW"
    },
    {
      "rcept_no": "20241114002984",
      "reprt_code": "11014",
      "bsns_year": "2024",
      "corp_code": "00688996",
      "stock_code": "105560",
      "fs_div": "CFS",
      "fs_nm": "연결재무제표",
      "sj_div": "IS",
      "sj_nm": "손익계산서",
      "account_nm": "이자수익",
      "thstrm_nm": "제 17 기3분기",
      "thstrm_dt": "2024.01.01 ~ 2024.09.30",
      "thstrm_amount": "7,637,802,000,000",
      "thstrm_add_amount": "22,863,335,000,000",
      "frmtrm_nm": "제 16 기3분기",
      "frmtrm_dt": "2023.01.01 ~ 2023.09.30",
      "frmtrm_add_amount": "21,410,551,000,000",
      "frmtrm_amount": "7,413,308,000,000",
      "ord": "53",
      "currency": "KRW"
    },
    {
      "rcept_no": "20241114002984",
      "reprt_code": "11014",
      "bsns_year": "2024",
      "corp_code": "00688996",
      "stock_code": "105560",
      "fs_div": "CFS",
      "fs_nm": "연결재무제표",
      "sj_div": "IS",
      "sj_nm": "손익계산서",
      "account_nm": "이자비용",
      "thstrm_nm": "제 17 기3분기",
      "thstrm_dt": "2024.01.01 ~ 2024.09.30",
      "thstrm_amount": "4,472,835,000,000",
      "thstrm_add_amount": "13,340,646,000,000",
      "frmtrm_nm": "제 16 기3분기",
      "frmtrm_dt": "2023.01.01 ~ 2023.09.30",
      "frmtrm_add_amount": "12,452,234,000,000",
      "frmtrm_amount": "4,288,660,000,000",
      "ord": "55",
      "currency": "KRW"
    },
    {
      "rcept_no": "20241114002984",
      "reprt_code": "11014",
      "bsns_year": "2024",
      "corp_code": "00688996",
      "stock_code": "105560",
      "fs_div": "CFS",
      "fs_nm": "연결재무제표",
      "sj_div": "IS",
      "sj_nm": "손익계산서",
      "account_nm": "영업이익(손실)",
      "thstrm_nm": "제 17 기3분기",
      "thstrm_dt": "2024.01.01 ~ 2024.09.30",
      "thstrm_amount": "2,357,551,000,000",
      "thstrm_add_amount": "7,015,248,000,000",
      "frmtrm_nm": "제 16 기3분기",
      "frmtrm_dt": "2023.01.01 ~ 2023.09.30",
      "frmtrm_add_amount": "6,139,347,000,000",
      "frmtrm_amount": "1,946,498,000,000",
      "ord": "59",
      "currency": "KRW"
    },
    {
      "rcept_no": "20241114002984",
      "reprt_code": "11014",
      "bsns_year": "2024",
      "corp_code": "00688996",
      "stock_code": "105560",
      "fs_div": "CFS",
      "fs_nm": "연결재무제표",
      "sj_div": "IS",
      "sj_nm": "손익계산서",
      "account_nm": "당기순이익(손실)",
      "thstrm_nm": "제 17 기3분기",
      "thstrm_dt": "2024.01.01 ~ 2024.09.30",
      "thstrm_amount": "1,596,039,000,000",
      "thstrm_add_amount": "4,369,918,000,000",
      "frmtrm_nm": "제 16 기3분기",
      "frmtrm_dt": "2023.01.01 ~ 2023.09.30",
      "frmtrm_add_amount": "4,352,027,000,000",
      "frmtrm_amount": "1,337,105,000,000",
      "ord": "61",
      "currency": "KRW"
    },
    {
      "rcept_no": "20241114002984",
      "reprt_code": "11014",
      "bsns_year": "2024",
      "corp_code": "00688996",
      "stock_code": "105560",
      "fs_div": "CFS",
      "fs_nm": "연결재무제표",
      "sj_div": "IS",
      "sj_nm": "손익계산서",
      "account_nm": "총포괄손익",
      "thstrm_nm": "제 17 기3분기",
      "thstrm_dt": "2024.01.01 ~ 2024.09.30",
      "thstrm_amount": "1,333,711,000,000",
      "thstrm_add_amount": "2,586,587,000,000",
      "frmtrm_nm": "제 16 기3분기",
      "frmtrm_dt": "2023.01.01 ~ 2023.09.30",
      "frmtrm_add_amount": "5,164,721,000,000",
      "frmtrm_amount": "1,523,028,000,000",
      "ord": "63",
      "currency": "KRW"
    },
    {
      "rcept_no": "20241114002984",
      "reprt_code": "11014",
      "bsns_year": "2024",
      "corp_code": "00688996",
      "stock_code": "105560",
      "fs_div": "CFS",
      "fs_nm": "연결재무제표",
      "sj_div": "IS",
      "sj_nm": "손익계산서",
      "account_nm": "순수수료손익",
      "thstrm_nm": "제 17 기3분기",
      "thstrm_dt": "2024.01.01 ~ 2024.09.30",
      "thstrm_amount": "942,704,000,000",
      "thstrm_add_amount": "2,852,432,000,000",
      "frmtrm_nm": "제 16 기3분기",
      "frmtrm_dt": "2023.01.01 ~ 2023.09.30",
      "frmtrm_add_amount": "2,766,821,000,000",
      "frmtrm_amount": "901,411,000,000",
      "ord": "67",
      "currency": "KRW"
    }
  ]
}